README.rst
setup.cfg
setup.py
docs/CHANGES.txt
docs/CONTRIBUTORS.txt
docs/INSTALL.txt
docs/LICENSE.GPL
docs/LICENSE.txt
pas/__init__.py
pas.plugins.wikid.egg-info/PKG-INFO
pas.plugins.wikid.egg-info/SOURCES.txt
pas.plugins.wikid.egg-info/dependency_links.txt
pas.plugins.wikid.egg-info/entry_points.txt
pas.plugins.wikid.egg-info/namespace_packages.txt
pas.plugins.wikid.egg-info/not-zip-safe
pas.plugins.wikid.egg-info/requires.txt
pas.plugins.wikid.egg-info/top_level.txt
pas/plugins/__init__.py
pas/plugins/wikid/README.txt
pas/plugins/wikid/WiKID-ca.pem
pas/plugins/wikid/__init__.py
pas/plugins/wikid/configure.zcml
pas/plugins/wikid/install.py
pas/plugins/wikid/interface.py
pas/plugins/wikid/plugin.py
pas/plugins/wikid/pywClient.py
pas/plugins/wikid/tests.py
pas/plugins/wikid/browser/__init__.py
pas/plugins/wikid/browser/configure.zcml
pas/plugins/wikid/browser/icon.gif
pas/plugins/wikid/plugins/__init__.py
pas/plugins/wikid/www/WiKID.png
pas/plugins/wikid/www/config.zpt
pas/plugins/wikid/www/wikidAdd.zpt