Metadata-Version: 1.0
Name: pas.plugins.wikid
Version: 0.1
Summary: This is a WiKID Strong Authentication System Plugin for the Zope2 Pluggable Authentication Service (PAS).
Home-page: https://github.com/collective/pas.plugins.wikid
Author: Quintagroup
Author-email: support@quintagroup.com
License: GPL
Platform: UNKNOWN
Classifier: Framework :: Plone
Classifier: Intended Audience :: Developers
Classifier: License :: OSI Approved :: GNU General Public License (GPL)
